flowfunc/Flowfunc.py
flowfunc/__init__.py
flowfunc/_imports_.py
flowfunc/config.py
flowfunc/distributed.py
flowfunc/exceptions.py
flowfunc/flowfunc.min.js
flowfunc/flowfunc.min.js.map
flowfunc/jobrunner.py
flowfunc/metadata.json
flowfunc/models.py
flowfunc/package-info.json
flowfunc/types.py
flowfunc/utils.py
flowfunc-0.1.5.dist-info/LICENSE
flowfunc-0.1.5.dist-info/METADATA
flowfunc-0.1.5.dist-info/WHEEL
flowfunc-0.1.5.dist-info/top_level.txt
flowfunc-0.1.5.dist-info/RECORD
