Metadata-Version: 2.2
Name: flowfunc
Version: 0.1.5
Summary: Dash wrapper for flume node editor
Author: Najeem Muhammed <najeem@gmail.com>
License: MIT
Classifier: Framework :: Dash
Requires-Python: >=3.10
License-File: LICENSE
Requires-Dist: pydantic<3,>=2
Provides-Extra: distributed
Requires-Dist: rq>=1.11; extra == "distributed"
Provides-Extra: full
Requires-Dist: dash>=2.6; extra == "full"
Requires-Dist: rq>=1.11; extra == "full"
Dynamic: author
Dynamic: classifier
Dynamic: description
Dynamic: description-content-type
Dynamic: license
Dynamic: provides-extra
Dynamic: requires-dist
Dynamic: requires-python
Dynamic: summary
